allsortalgo/__init__.py
allsortalgo/core.py
allsortalgo/helpers.py
allsortalgo-0.0.1.dist-info/DESCRIPTION.rst
allsortalgo-0.0.1.dist-info/METADATA
allsortalgo-0.0.1.dist-info/RECORD
allsortalgo-0.0.1.dist-info/WHEEL
allsortalgo-0.0.1.dist-info/metadata.json
allsortalgo-0.0.1.dist-info/top_level.txt
