Metadata-Version: 2.0
Name: allsortalgo
Version: 0.0.1
Summary: Python package containing implementation of all sorting algorithms
Home-page: https://github.com/sannykr/allsortalgo
Author: Sanny Kumar
Author-email: sanny.iitkgp@gmail.com
License: Copyright 2017    Sanny Kumar
